stat_lib/Table_Arp_Madore_pairs_updated.txt
stat_lib/__init__.py
stat_lib/__init__old.py
stat_lib/iDR4_obs_seeing.csv
stat_lib/iDR4_zero-points.csv
stat_lib/properties.dat
stat_lib/zero_points.fits
stat_lib/__pycache__/__init__.cpython-38.pyc
stat_lib/__pycache__/stat_lib.cpython-38.pyc
astromorphlib-1.0.10.dist-info/LICENSE.txt
astromorphlib-1.0.10.dist-info/METADATA
astromorphlib-1.0.10.dist-info/WHEEL
astromorphlib-1.0.10.dist-info/top_level.txt
astromorphlib-1.0.10.dist-info/RECORD
