Metadata-Version: 2.1
Name: astromorphlib
Version: 1.0.10
Summary: Python scripts to analyze the morphology of isolated/interacting galaxies
Home-page: https://gitlab.com/joseaher/astromorphlib
Author: J. A. Hernandez-Jimenez
Author-email: joseaher@gmail.com
License-File: LICENSE.txt
